advanced_template_filters/__init__.py
advanced_template_filters/apps.py
advanced_template_filters/tests.py
advanced_template_filters/templatetags/__init__.py
advanced_template_filters/templatetags/advanced_template_filters.py
advanced_template_tags/__init__.py
advanced_template_tags/apps.py
advanced_template_tags/tests.py
advanced_template_tags/templatetags/__init__.py
advanced_template_tags/templatetags/advanced_template_tags.py
django_advanced_template_tags-0.1.dist-info/DESCRIPTION.rst
django_advanced_template_tags-0.1.dist-info/METADATA
django_advanced_template_tags-0.1.dist-info/RECORD
django_advanced_template_tags-0.1.dist-info/WHEEL
django_advanced_template_tags-0.1.dist-info/metadata.json
django_advanced_template_tags-0.1.dist-info/top_level.txt
