Metadata-Version: 2.0
Name: django-advanced-template-tags
Version: 0.1
Summary: Provides some useful template tags that are missing in the Django builtins.
Home-page: https://github.com/Nereo/django-advanced-template-tags
Author: François Voron
Author-email: francois.voron@nereo.fr
License: MIT License
Platform: UNKNOWN
Classifier: Environment :: Web Environment
Classifier: Framework :: Django
Classifier: Framework :: Django :: 1.10
Classifier: Intended Audience :: Developers
Classifier: License :: OSI Approved :: MIT License
Classifier: Operating System :: OS Independent
Classifier: Programming Language :: Python
Classifier: Programming Language :: Python :: 3
Classifier: Programming Language :: Python :: 3.4
Classifier: Programming Language :: Python :: 3.5
Classifier: Topic :: Internet :: WWW/HTTP
Classifier: Topic :: Internet :: WWW/HTTP :: Dynamic Content
